poly_decomp/__init__.py
poly_decomp/poly_decomp.py
poly_decomp/utils.py
poly_decomp-0.0.1.dist-info/DESCRIPTION.rst
poly_decomp-0.0.1.dist-info/METADATA
poly_decomp-0.0.1.dist-info/RECORD
poly_decomp-0.0.1.dist-info/WHEEL
poly_decomp-0.0.1.dist-info/metadata.json
poly_decomp-0.0.1.dist-info/top_level.txt
